sbm_vbem/Model_functions.py
sbm_vbem/Model_functions_vem.py
sbm_vbem/SBM.py
sbm_vbem/__init__.py
sbm_vbem/utils.py
sbm_vbem-0.0.12.dist-info/METADATA
sbm_vbem-0.0.12.dist-info/WHEEL
sbm_vbem-0.0.12.dist-info/licenses/LICENSE
sbm_vbem-0.0.12.dist-info/RECORD
