Metadata-Version: 2.1
Name: SBM_VBEM
Version: 0.0.12
Summary: Implementation of Stochastic Block Model with several inference strategy (VBEM, VEM, Natural conjugate gradients)
Project-URL: Homepage, https://github.com/Remi-Boutin/SBM_package
Project-URL: Bug Tracker, https://github.com/Remi-Boutin/SBM_package/issues
Author-email: Remi Boutin <remi.boutin.stat@gmail.com>
License-File: LICENSE
Classifier: License :: OSI Approved :: MIT License
Classifier: Operating System :: OS Independent
Classifier: Programming Language :: Python :: 3
Requires-Python: >=3.1
